os_normalizer/__init__.py
os_normalizer/constants.py
os_normalizer/cpe.py
os_normalizer/helpers.py
os_normalizer/models.py
os_normalizer/os_normalizer.py
os_normalizer/parsers/__init__.py
os_normalizer/parsers/bsd.py
os_normalizer/parsers/esxi.py
os_normalizer/parsers/linux.py
os_normalizer/parsers/macos.py
os_normalizer/parsers/mobile.py
os_normalizer/parsers/solaris.py
os_normalizer/parsers/windows.py
os_normalizer/parsers/network/__init__.py
os_normalizer/parsers/network/cisco.py
os_normalizer/parsers/network/fortinet.py
os_normalizer/parsers/network/huawei.py
os_normalizer/parsers/network/juniper.py
os_normalizer/parsers/network/netgear.py
os_normalizer-0.5.1.dist-info/METADATA
os_normalizer-0.5.1.dist-info/WHEEL
os_normalizer-0.5.1.dist-info/licenses/LICENSE
os_normalizer-0.5.1.dist-info/RECORD
