Metadata-Version: 2.4
Name: os-normalizer
Version: 0.5.1
Summary: Normalize raw OS strings/metadata into structured data (family, product, version, arch).
Project-URL: Homepage, https://github.com/johnscillieri/os-normalizer
Project-URL: Repository, https://github.com/johnscillieri/os-normalizer
Project-URL: Issues, https://github.com/johnscillieri/os-normalizer/issues
Project-URL: Changelog, https://github.com/johnscillieri/os-normalizer/releases
License: MIT License
License-File: LICENSE
Keywords: cpe,fingerprint,normalize,os,parsing
Classifier: Development Status :: 4 - Beta
Classifier: Intended Audience :: Developers
Classifier: License :: OSI Approved :: MIT License
Classifier: Programming Language :: Python
Classifier: Programming Language :: Python :: 3
Classifier: Programming Language :: Python :: 3 :: Only
Classifier: Programming Language :: Python :: 3.11
Classifier: Programming Language :: Python :: 3.12
Classifier: Programming Language :: Python :: 3.13
Classifier: Programming Language :: Python :: 3.14
Classifier: Topic :: Software Development :: Libraries
Classifier: Topic :: System :: Operating System
Requires-Python: >=3.11
